zopfli/__init__.py
zopfli/_version.py
zopfli/gzip.py
zopfli/png.py
zopfli/zlib.py
zopfli/zopfli.pypy311-pp73-aarch64-linux-gnu.so
zopfli-0.4.0.dist-info/COPYING
zopfli-0.4.0.dist-info/METADATA
zopfli-0.4.0.dist-info/WHEEL
zopfli-0.4.0.dist-info/top_level.txt
zopfli-0.4.0.dist-info/zip-safe
zopfli-0.4.0.dist-info/RECORD
