Metadata-Version: 2.1
Name: zopfli
Version: 0.4.0
Summary: Zopfli module for python
Home-page: https://github.com/fonttools/py-zopfli
Author: Adam DePrince
Author-email: deprince@googlealumni.com
Maintainer: Cosimo Lupo
Maintainer-email: cosimo@anthrotype.com
License: Apache-2.0
Classifier: Intended Audience :: Developers
Classifier: License :: OSI Approved :: Apache Software License
Classifier: Programming Language :: Python :: 3
Classifier: Programming Language :: Python :: 3.10
Classifier: Programming Language :: Python :: 3.11
Classifier: Programming Language :: Python :: 3.12
Classifier: Programming Language :: Python :: 3.13
Classifier: Programming Language :: Python :: 3.14
Classifier: Programming Language :: Python :: Implementation :: CPython
Classifier: Programming Language :: Python :: Implementation :: PyPy
Classifier: Topic :: System :: Archiving :: Compression
Requires-Python: >=3.10
License-File: COPYING
Provides-Extra: test
Requires-Dist: pytest ; extra == 'test'
